caseine_design/__init__.py
caseine_design/decorations.py
caseine_design-0.0.5.dist-info/LICENSE
caseine_design-0.0.5.dist-info/METADATA
caseine_design-0.0.5.dist-info/WHEEL
caseine_design-0.0.5.dist-info/top_level.txt
caseine_design-0.0.5.dist-info/RECORD
