Metadata-Version: 2.1
Name: caseine-design
Version: 0.0.5
Summary: A set of decorations used for the VPL Design Plugin on caseine platform.
Home-page: https://gricad-gitlab.univ-grenoble-alpes.fr/caseine/vpl_design_plugin
Author: Gilles Sérasset
Author-email: Gilles.Serasset@univ-grenoble-alpes.fr
License: UNKNOWN
Platform: UNKNOWN
Classifier: Programming Language :: Python :: 3
Classifier: License :: OSI Approved :: MIT License
Classifier: Operating System :: OS Independent
Requires-Python: >=3.6
